generalmap/GeneralMap.py
generalmap/__init__.py
generalmap-1.0.2.dist-info/METADATA
generalmap-1.0.2.dist-info/RECORD
generalmap-1.0.2.dist-info/WHEEL
generalmap-1.0.2.dist-info/top_level.txt
