Metadata-Version: 2.1
Name: generalmap
Version: 1.0.2
Summary: A generalized map function for lift function over structures
Home-page: https://github.com/tidues/GeneralizedMapFunction
Author: Tidues Wei
Author-email: tidues@gmail.com
License: UNKNOWN
Platform: UNKNOWN
Classifier: Programming Language :: Python :: 3
Classifier: License :: OSI Approved :: MIT License
Classifier: Operating System :: OS Independent
